fastapi_di/__init__.py
fastapi_di/concurrency.py
fastapi_di/injector.py
fastapi_di/protocols.py
fastapi_di/task.py
fastapi_di/utils.py
fastapi_di-0.0.1.dist-info/WHEEL
fastapi_di-0.0.1.dist-info/METADATA
fastapi_di-0.0.1.dist-info/RECORD
