Metadata-Version: 2.1
Name: fastapi-di
Version: 0.0.1
Summary: Extracted the dependency injection process from fastapi.
Home-page: https://github.com/sasano8/fastapi_di
License: MIT
Author: sasano8
Author-email: y-sasahara@ys-method.com
Requires-Python: >=3.8,<4.0
Classifier: License :: OSI Approved :: MIT License
Classifier: Programming Language :: Python :: 3
Classifier: Programming Language :: Python :: 3.8
Requires-Dist: fastapi (>=0.63.0,<0.64.0)
Requires-Dist: pydantic (>=1.8.1,<2.0.0)
Project-URL: Repository, https://github.com/sasano8/fastapi_di
